freaky/__init__.py
freaky/compare.py
freaky/decode.py
freaky/encode.py
freaky/entropy.py
freaky-1.0.0a11.dist-info/METADATA
freaky-1.0.0a11.dist-info/WHEEL
freaky-1.0.0a11.dist-info/entry_points.txt
freaky-1.0.0a11.dist-info/top_level.txt
freaky-1.0.0a11.dist-info/RECORD
