Metadata-Version: 2.1
Name: freaky
Version: 1.0.0a11
Summary: tools for frequency domain analysis of audio.
Author-email: Leslie Schumm <lschumm@protonmail.com>
License: GPL-2.0-only
Requires-Dist: click
Requires-Dist: numpy
Requires-Dist: scipy
Requires-Dist: numba
Requires-Dist: pillow
